mkdocstrings_handlers/pac_handler/__init__.py
mkdocstrings_handlers/pac_handler/handler.py
mkdocstrings_handlers/pac_handler/templates/mkdocs/function_template.html
mkdocstrings_pac-1.0.2.dist-info/WHEEL
mkdocstrings_pac-1.0.2.dist-info/METADATA
mkdocstrings_pac-1.0.2.dist-info/licenses/LICENSE
mkdocstrings_pac-1.0.2.dist-info/RECORD
